htmllogging/__init__.py
htmllogging-0.0.1.dist-info/LICENSE
htmllogging-0.0.1.dist-info/METADATA
htmllogging-0.0.1.dist-info/WHEEL
htmllogging-0.0.1.dist-info/top_level.txt
htmllogging-0.0.1.dist-info/RECORD
