Metadata-Version: 2.1
Name: htmllogging
Version: 0.0.1
Summary: Logging into HTML format.
Home-page: https://www.benderrobotics.com
Author: Bender Robotics
Author-email: kumpan@benderrobotics.com
License: UNKNOWN
Platform: UNKNOWN
Classifier: Programming Language :: Python :: 3
Classifier: License :: OSI Approved :: MIT License
Classifier: Operating System :: OS Independent
Requires-Python: >=3.6
License-File: LICENSE
Requires-Dist: Pillow>=6.2.1
